JXAutoML/JiaoCheng.py
JXAutoML/JiaoChengB.py
JXAutoML/JiaoCheng_10CV.py
JXAutoML/NingXiang.py
JXAutoML/YangZhouB.py
JXAutoML/YangZhouB_10CV.py
JXAutoML/__init__.py
JXAutoML-0.4.5.dist-info/LICENSE
JXAutoML-0.4.5.dist-info/METADATA
JXAutoML-0.4.5.dist-info/WHEEL
JXAutoML-0.4.5.dist-info/top_level.txt
JXAutoML-0.4.5.dist-info/RECORD
