Metadata-Version: 2.1
Name: JXAutoML
Version: 0.4.5
Summary: Advanced HyperParameter Tuning
Home-page: https://github.com/TGChenZP/JXAutoML
Author: Lang Chen
Author-email: ronchen6666@gmail.com
License: UNKNOWN
Platform: UNKNOWN
Classifier: Programming Language :: Python :: 3
Classifier: License :: OSI Approved :: MIT License
Classifier: Operating System :: OS Independent
Requires-Python: >=3.6
License-File: LICENSE
